simplesimdb.py
simplesimdb-1.1.1.dist-info/METADATA
simplesimdb-1.1.1.dist-info/WHEEL
simplesimdb-1.1.1.dist-info/licenses/LICENSE
simplesimdb-1.1.1.dist-info/RECORD
