Metadata-Version: 2.3
Name: simplesimdb
Version: 1.1.1
Summary: Create, access and manage simple simulation data
Project-URL: Source, https://github.com/mwiesenberger/simplesimdb
Project-URL: Tracker, https://github.com/mwiesenberger/simplesimdb/issues
Author-email: Matthias Wiesenberger <mattwi@fysik.dtu.dk>
License: MIT License
Classifier: License :: OSI Approved :: MIT License
Classifier: Operating System :: OS Independent
Classifier: Programming Language :: Python :: 3
Classifier: Topic :: Database
Classifier: Topic :: Scientific/Engineering
Classifier: Topic :: Software Development :: Libraries
Classifier: Topic :: Utilities
Requires-Python: >=3.10
Provides-Extra: test
Requires-Dist: pytest; extra == 'test'
